flower_crane-0.5.4.dist-info/METADATA
flower_crane-0.5.4.dist-info/WHEEL
flower_crane.libs/libgcc_s-5b5488a6.so.1
flower_crane/__init__.py
flower_crane/__init__.pyi
flower_crane/py.typed
flower_crane/flower_crane.cpython-312-arm-linux-musleabihf.so
flower_crane-0.5.4.dist-info/RECORD
